pyholdsport/__init__.py
pyholdsport/holdsport.py
pyholdsport/models.py
pyholdsport/py.typed
pyholdsport-0.0.6.dist-info/WHEEL
pyholdsport-0.0.6.dist-info/METADATA
pyholdsport-0.0.6.dist-info/RECORD
