Metadata-Version: 2.3
Name: pyholdsport
Version: 0.0.6
Summary: Unofficial python library for interacting with holdsport.
Author: Daniel Mizsak
Author-email: Daniel Mizsak <info@pythonvilag.hu>
License: MIT License
Requires-Dist: httpx==0.28.1
Requires-Dist: pydantic==2.12.5
Requires-Python: >=3.10
Project-URL: Issues, https://github.com/daniel-mizsak/pyholdsport/issues
Project-URL: Repository, https://github.com/daniel-mizsak/pyholdsport
